requests_auth_aws_sigv4/__init__.py
requests_auth_aws_sigv4/__main__.py
requests_auth_aws_sigv4-0.7.dist-info/LICENSE
requests_auth_aws_sigv4-0.7.dist-info/METADATA
requests_auth_aws_sigv4-0.7.dist-info/WHEEL
requests_auth_aws_sigv4-0.7.dist-info/top_level.txt
requests_auth_aws_sigv4-0.7.dist-info/RECORD
